pravo_api/__init__.py
pravo_api/worker.py
pravo_api/api/__init__.py
pravo_api/api/config.py
pravo_api/api/main.py
pravo_api/api/api_data/gov_bodies_n_their_codes.json
pravo_api/api/api_data/regions.txt
pravo_api/api/api_data/regions_n_their_numbers.json
pravo_api/api/downloader/__init__.py
pravo_api/api/downloader/aio_downloader.py
pravo_api/api/downloader/meta_data_getter.py
pravo_api/api/links_getter/__init__.py
pravo_api/api/links_getter/links_getter.py
pravo_api/api/links_getter/models.py
pravo_api/api/utils/__init__.py
pravo_api/api/utils/back_off.py
pravo_api/api/utils/my_logger.py
pravo_api/appoint_parser/__init__.py
pravo_api/appoint_parser/__main__.py
pravo_api/appoint_parser/decree_parser.py
pravo_api/appoint_parser/parsers/__init__.py
pravo_api/appoint_parser/parsers/multi_app.py
pravo_api/appoint_parser/parsers/single_appo.py
pravo_api/appoint_parser/tools/__init__.py
pravo_api/appoint_parser/tools/name_parser.py
pravo_api/appoint_parser/tools/text_cleaner.py
pravo_api/appoint_parser/tools/unwanted_words.txt
pravo_api/appoint_parser/tools/unwanted_words_for_names.txt
pravo_api/appoint_parser/utils/__init__.py
pravo_api/appoint_parser/utils/models.py
pravo_api/appoint_parser/utils/my_logger.py
pravo_api-0.0.17.dist-info/LICENSE
pravo_api-0.0.17.dist-info/METADATA
pravo_api-0.0.17.dist-info/WHEEL
pravo_api-0.0.17.dist-info/top_level.txt
pravo_api-0.0.17.dist-info/RECORD
